tab_right/__init__.py
tab_right/task_detection.py
tab_right/base_architecture/__init__.py
tab_right/base_architecture/drift_plot_protocols.py
tab_right/base_architecture/drift_protocols.py
tab_right/base_architecture/seg_plotting_protocols.py
tab_right/base_architecture/seg_protocols.py
tab_right/drift/__init__.py
tab_right/drift/cramer_v.py
tab_right/drift/drift_calculator.py
tab_right/drift/psi.py
tab_right/drift/univariate.py
tab_right/plotting/__init__.py
tab_right/plotting/drift_plotter.py
tab_right/plotting/plot_drift.py
tab_right/plotting/plot_feature_drift.py
tab_right/plotting/plot_segmentations.py
tab_right/segmentations/__init__.py
tab_right/segmentations/calc_seg.py
tab_right/segmentations/double_seg.py
tab_right-0.0.2b0.dist-info/METADATA
tab_right-0.0.2b0.dist-info/WHEEL
tab_right-0.0.2b0.dist-info/licenses/LICENSE
tab_right-0.0.2b0.dist-info/RECORD
