Metadata-Version: 2.4
Name: tab-right
Version: 0.0.2b0
Summary: A Python package for easy analysis of tabular data for inference models, focusing on model-agnostic diagnostics using predictions.
Author-email: DanielAvdar <66269169+DanielAvdar@users.noreply.github.com>
License: MIT
License-File: LICENSE
Keywords: python
Classifier: License :: OSI Approved :: MIT License
Classifier: Operating System :: OS Independent
Classifier: Programming Language :: Python :: 3
Classifier: Programming Language :: Python :: 3.10
Classifier: Programming Language :: Python :: 3.11
Classifier: Programming Language :: Python :: 3.12
Classifier: Programming Language :: Python :: 3.13
Requires-Python: >=3.9
Requires-Dist: pandas
Requires-Dist: scikit-learn>=1.6
Provides-Extra: plotly
Requires-Dist: matplotlib>=3.0.0; extra == 'plotly'
Requires-Dist: plotly>=5.0.0; extra == 'plotly'
